madata/__init__.py
madata/metadata.py
madata-0.2.0.dist-info/LICENSE
madata-0.2.0.dist-info/METADATA
madata-0.2.0.dist-info/WHEEL
madata-0.2.0.dist-info/top_level.txt
madata-0.2.0.dist-info/RECORD
