Metadata-Version: 2.1
Name: madata
Version: 0.2.0
Summary: A tool for syncing the dataset-metadata between MADATA and Wikidata
Home-page: https://github.com/UB-Mannheim/madata
Author: Renat Shigapov
License: MIT
Classifier: Programming Language :: Python :: 3
Classifier: License :: OSI Approved :: MIT License
Classifier: Operating System :: OS Independent
Requires-Python: >=3.7
License-File: LICENSE
Requires-Dist: sickle
Requires-Dist: pandas
Requires-Dist: requests
Requires-Dist: wikidataintegrator
Requires-Dist: tqdm
Requires-Dist: appengine-python-standard
